code_util/__init__.py
code_util/apidoc_generation.py
code_util/buffer.py
code_util/buffer_redis.py
code_util/env.py
code_util/file.py
code_util/log.py
code_util/markdown.py
code_util/num.py
code_util/plot.py
code_util/setup.py
code_util/str_adv.py
code_util/structures.py
ml2_util/MLModel.py
ml2_util/__init__.py
ml2_util/metrics.py
ml2_util/setup.py
ml2_util/mlconfig_components/__init__.py
ml2_util/mlconfig_components/model_save_process.py
ml2_util/mlconfig_components/train_report_process.py
ml2_util/mlmodel_components/__init__.py
ml2_util/mlmodel_components/tf_modelgraph.py
ml2_util/mlmodel_components/tf_modelstorage.py
ml_util/IterationProcess.py
ml_util/IterationProcessModelBase.py
ml_util/MLComponentBase.py
ml_util/MetricsBase.py
ml_util/TrainableProcess.py
ml_util/TrainableProcessModelBase.py
ml_util/__init__.py
ml_util/metrics/__init__.py
ml_util/metrics/accuracy_metrics.py
ml_util/metrics/precision_metrics.py
nlp_util/BertModelBase.py
nlp_util/TFModelBase.py
nlp_util/__init__.py
nlp_util/default_process.py
nlp_util/setup.py
nlp_util/components/BertEmbedding.py
nlp_util/components/Embedding.py
nlp_util/components/SentenceCut.py
nlp_util/components/WordCut.py
nlp_util/components/__init__.py
nlp_util/piplines/__init__.py
nlp_util/piplines/text_generator.py
sample_util/MinioSampleSource.py
sample_util/NLSampleSource.py
sample_util/RandomSet.py
sample_util/SSHSampleSource.py
sample_util/SampleSet.py
sample_util/SampleSet_Util.py
sample_util/SampleSet_import.py
sample_util/__init__.py
sample_util/samples_lib.py
sample_util/setup.py
spider_util/WebGetter.py
spider_util/__init__.py
spider_util/setup.py
jutool.sample_util-0.2.26.dist-info/LICENSE
jutool.sample_util-0.2.26.dist-info/METADATA
jutool.sample_util-0.2.26.dist-info/WHEEL
jutool.sample_util-0.2.26.dist-info/top_level.txt
jutool.sample_util-0.2.26.dist-info/RECORD
